gde/__init__.py
gde/__main__.py
gde/_gde_version.py
gde/gui.py
gde/qt.py
gde-1.0.3.dist-info/LICENSE.txt
gde-1.0.3.dist-info/METADATA
gde-1.0.3.dist-info/WHEEL
gde-1.0.3.dist-info/entry_points.txt
gde-1.0.3.dist-info/top_level.txt
gde-1.0.3.dist-info/RECORD
