Metadata-Version: 2.1
Name: gde
Version: 1.0.3
Summary: Graph Data Exctractor (GDE)
Home-page: UNKNOWN
Author: Michael Clerx
Author-email: michael@myokit.org
License: BSD 3-clause license
Platform: UNKNOWN
Classifier: Development Status :: 5 - Production/Stable
Classifier: Intended Audience :: Science/Research
Classifier: License :: OSI Approved :: BSD License
Classifier: Operating System :: OS Independent
Classifier: Programming Language :: Python :: 3
Classifier: Topic :: Scientific/Engineering
Requires-Python: >=3.5
License-File: LICENSE.txt
Requires-Dist: configparser
Requires-Dist: numpy
Requires-Dist: pyqt5
Requires-Dist: setuptools
Requires-Dist: sip
